adminlte2_admin/__init__.py
adminlte2_admin/static/adminlte2_admin/css/change_list.css
adminlte2_admin/static/adminlte2_admin/css/delete_confirmation.css
adminlte2_admin/static/adminlte2_admin/css/delete_selected_confirmation.css
adminlte2_admin/static/adminlte2_admin/css/forms.css
adminlte2_admin/static/adminlte2_admin/css/index.css
adminlte2_admin/static/adminlte2_admin/css/responsive.css
adminlte2_admin/static/adminlte2_admin/js/base_site.js
adminlte2_admin/static/adminlte2_admin/js/change_list.js
adminlte2_admin/templates/admin/base.html
adminlte2_admin/templates/admin/base_site.html
adminlte2_admin/templates/admin/change_form.html
adminlte2_admin/templates/admin/change_list.html
adminlte2_admin/templates/admin/delete_confirmation.html
adminlte2_admin/templates/admin/delete_selected_confirmation.html
adminlte2_admin/templates/admin/index.html
adminlte2_admin/templates/admin/login.html
adminlte2_admin/templates/admin/object_history.html
adminlte2_admin/templates/admin/auth/user/change_password.html
adminlte2_admin/templates/admin/components/header.html
adminlte2_admin/templates/admin/components/sidebar.html
adminlte2_admin/templates/admin/includes/fieldset.html
adminlte2_admin/templates/admin/widgets/related_widget_wrapper.html
adminlte2_admin/templates/registration/password_change_form.html
adminlte2_admin/templates/registration/password_reset_confirm.html
adminlte2_admin/templates/registration/password_reset_form.html
adminlte2_templates/__init__.py
adminlte2_templates/constants.py
adminlte2_templates/context_processors.py
adminlte2_templates/core.py
adminlte2_templates/static/adminlte2/fix/header_dropdown_link_color.css
adminlte2_templates/static/adminlte2/fix/sidebar_link_word_wrap.css
adminlte2_templates/static/adminlte2/libs/adminlte-2.4.18/css/adminlte.css
adminlte2_templates/static/adminlte2/libs/adminlte-2.4.18/css/adminlte.css.map
adminlte2_templates/static/adminlte2/libs/adminlte-2.4.18/css/adminlte.min.css
django_adminlte2_templates-1.4.0.dist-info/LICENSE
django_adminlte2_templates-1.4.0.dist-info/METADATA
django_adminlte2_templates-1.4.0.dist-info/WHEEL
django_adminlte2_templates-1.4.0.dist-info/top_level.txt
django_adminlte2_templates-1.4.0.dist-info/RECORD
