Metadata-Version: 2.1
Name: django-adminlte2-templates
Version: 1.4.0
Summary: AdminLTE 2 templates for Django
Home-page: https://github.com/josemarimanio/django-adminlte2-templates/
Author: Jose Mari Manio
Author-email: josemari.manio@tutamail.com
License: MIT
Project-URL: Documentation, https://django-adminlte2-templates.readthedocs.io/en/latest/
Project-URL: Source Code, https://github.com/josemarimanio/django-adminlte2-templates/
Platform: UNKNOWN
Classifier: Development Status :: 5 - Production/Stable
Classifier: Environment :: Web Environment
Classifier: Framework :: Django :: 1.11
Classifier: Framework :: Django :: 2.2
Classifier: Framework :: Django :: 3.0
Classifier: Intended Audience :: Developers
Classifier: License :: OSI Approved :: MIT License
Classifier: Operating System :: OS Independent
Classifier: Programming Language :: Python :: 2.7
Classifier: Programming Language :: Python :: 3
Classifier: Programming Language :: Python :: 3.4
Classifier: Programming Language :: Python :: 3.5
Classifier: Programming Language :: Python :: 3.6
Classifier: Programming Language :: Python :: 3.7
Classifier: Programming Language :: Python :: 3.8
Classifier: Topic :: Internet :: WWW/HTTP
Classifier: Topic :: Internet :: WWW/HTTP :: Dynamic Content
Requires-Python: >=2.7
